ppptoolbox/__init__.py
ppptoolbox/example.py
ppptoolbox-0.0.4.dist-info/WHEEL
ppptoolbox-0.0.4.dist-info/METADATA
ppptoolbox-0.0.4.dist-info/RECORD
