Metadata-Version: 2.3
Name: ppptoolbox
Version: 0.0.4
Summary: PashaPay Python Toolbox
Author: Ruslan Ağalarov
Author-email: Ruslan Ağalarov <ruslan.a@pashapay.az>
License: MIT
Classifier: Programming Language :: Python :: 3
Classifier: Operating System :: OS Independent
Requires-Python: >=3.9
Project-URL: Homepage, https://github.com/m10-payments/python-toolbox
